setup.py
pyther_maybe/__init__.py
pyther_maybe.egg-info/PKG-INFO
pyther_maybe.egg-info/SOURCES.txt
pyther_maybe.egg-info/dependency_links.txt
pyther_maybe.egg-info/top_level.txt