Metadata-Version: 1.0
Name: pyther-maybe
Version: 0.0.1
Summary: implementation of Maybe and Either data structures as python objects
Home-page: UNKNOWN
Author: UNKNOWN
Author-email: UNKNOWN
License: LGPLv3
Platform: UNKNOWN
